cptv/__init__.py
cptv/frame.py
cptv/reader.py
cptv/writer.py
cptv-1.5.4.dist-info/LICENSE
cptv-1.5.4.dist-info/METADATA
cptv-1.5.4.dist-info/WHEEL
cptv-1.5.4.dist-info/top_level.txt
cptv-1.5.4.dist-info/RECORD
