Metadata-Version: 2.1
Name: cptv
Version: 1.5.4
Summary: Python library for handling Cacophony Project Thermal Video (CPTV) files
Home-page: https://github.com/TheCacophonyProject/python-cptv
Author: The Cacophony Project
Author-email: dev@cacophony.org.nz
License: Apache License 2.0
Keywords: video compression
Classifier: Development Status :: 4 - Beta
Classifier: Intended Audience :: Developers
Classifier: License :: OSI Approved :: Apache Software License
Classifier: Programming Language :: Python :: 3
Classifier: Topic :: Software Development :: Libraries :: Python Modules
Classifier: Topic :: Multimedia :: Video :: Conversion
License-File: LICENSE
Requires-Dist: numpy
